pelican_xref/__init__.py
pelican_xref/pelican_xref.py
pelican_xref-0.1.1.dist-info/WHEEL
pelican_xref-0.1.1.dist-info/METADATA
pelican_xref-0.1.1.dist-info/RECORD
